.bzrignore
CHANGES.txt
LICENSE.GPL
LICENSE.txt
README.txt
bootstrap.py
buildout.cfg
setup.py
src/zw/__init__.py
src/zw.widget.egg-info/PKG-INFO
src/zw.widget.egg-info/SOURCES.txt
src/zw.widget.egg-info/dependency_links.txt
src/zw.widget.egg-info/namespace_packages.txt
src/zw.widget.egg-info/not-zip-safe
src/zw.widget.egg-info/requires.txt
src/zw.widget.egg-info/top_level.txt
src/zw/widget/__init__.py
src/zw/widget/configure.zcml
src/zw/widget/i18n.py
src/zw/widget/zw.widget-configure.zcml
src/zw/widget/color/README.txt
src/zw/widget/color/__init__.py
src/zw/widget/color/color_display.pt
src/zw/widget/color/color_input.pt
src/zw/widget/color/configure.zcml
src/zw/widget/color/interfaces.py
src/zw/widget/color/tests.py
src/zw/widget/color/widget.py
src/zw/widget/color/zw.widget.color-configure.zcml
src/zw/widget/email/README.txt
src/zw/widget/email/__init__.py
src/zw/widget/email/configure.zcml
src/zw/widget/email/email_display.pt
src/zw/widget/email/email_input.pt
src/zw/widget/email/interfaces.py
src/zw/widget/email/tests.py
src/zw/widget/email/widget.py
src/zw/widget/email/zw.widget.email-configure.zcml
src/zw/widget/lines/README.txt
src/zw/widget/lines/__init__.py
src/zw/widget/lines/configure.zcml
src/zw/widget/lines/converter.py
src/zw/widget/lines/interfaces.py
src/zw/widget/lines/lines_display.pt
src/zw/widget/lines/lines_input.pt
src/zw/widget/lines/tests.py
src/zw/widget/lines/widget.py
src/zw/widget/lines/zw.widget.lines-configure.zcml
src/zw/widget/tiny/README.txt
src/zw/widget/tiny/__init__.py
src/zw/widget/tiny/configure.zcml
src/zw/widget/tiny/interfaces.py
src/zw/widget/tiny/tests.py
src/zw/widget/tiny/tiny_display.pt
src/zw/widget/tiny/tiny_input.pt
src/zw/widget/tiny/widget.py
src/zw/widget/tiny/zw.widget.tiny-configure.zcml