Metadata-Version: 1.0
Name: zw.widget
Version: 0.1.6
Summary: Additional widgets for z3c.form
Home-page: https://launchpad.net/zw.widget
Author: Gregor Giesen
Author-email: giesen@zaehlwerk.net
License: GPLv3
Keywords: zope3
Platform: UNKNOWN
Classifier: Development Status :: 4 - Beta
Classifier: Programming Language :: Python
Classifier: Environment :: Web Environment
Classifier: Topic :: Internet :: WWW/HTTP :: WSGI :: Application
Classifier: Framework :: Zope3
Classifier: Intended Audience :: Developers
Classifier: License :: OSI Approved :: GNU General Public License (GPL)
